clig/__about__.py
clig/__init__.py
clig/clig.py
clig-0.6.0.dist-info/METADATA
clig-0.6.0.dist-info/WHEEL
clig-0.6.0.dist-info/licenses/LICENSE.txt
clig-0.6.0.dist-info/RECORD
