Metadata-Version: 2.4
Name: clig
Version: 0.6.0
Summary: Command Line Interface Generator
Project-URL: Documentation, https://github.com/diogo-rossi/clig
Project-URL: Issues, https://github.com/diogo-rossi/clig/issues
Project-URL: Source, https://github.com/diogo-rossi/clig
Author-email: Diogo Rossi <rossi.diogo@gmail.com>
License-Expression: MIT
License-File: LICENSE.txt
Classifier: Programming Language :: Python :: 3.12
Classifier: Programming Language :: Python :: Implementation :: CPython
Classifier: Programming Language :: Python :: Implementation :: PyPy
Requires-Python: >=3.12
